exact_cover_py/__init__.py
exact_cover_py/exact_cover-pointers.py
exact_cover_py/exact_cover.py
exact_cover_py/picture1.png
exact_cover_py/picture2.png
exact_cover_py-0.1.2.dist-info/METADATA
exact_cover_py-0.1.2.dist-info/WHEEL
exact_cover_py-0.1.2.dist-info/licenses/LICENSE
exact_cover_py-0.1.2.dist-info/RECORD
