Metadata-Version: 2.3
Name: exact_cover_py
Version: 0.1.2
Summary: Exact cover solver in Python
Project-URL: Homepage, https://github.com/parmentelat/exact-cover-py
Project-URL: Issues, https://github.com/parmentelat/exact-cover-py/issues
Author-email: Thierry Parmentelat <thierry.parmentelat@inria.fr>
License-Expression: CC-BY-NC-4.0
License-File: LICENSE
Classifier: Operating System :: OS Independent
Classifier: Programming Language :: Python :: 3
Requires-Python: >=3.10
Requires-Dist: numba
Requires-Dist: numpy
Provides-Extra: build
Requires-Dist: build; extra == 'build'
Requires-Dist: hatchling; extra == 'build'
Requires-Dist: twine; extra == 'build'
Provides-Extra: tests
Requires-Dist: exact-cover-samples; extra == 'tests'
Requires-Dist: pytest; extra == 'tests'
